storedqueries/__init__.py
django_storedqueries-0.1.4.dist-info/LICENSE
django_storedqueries-0.1.4.dist-info/METADATA
django_storedqueries-0.1.4.dist-info/WHEEL
django_storedqueries-0.1.4.dist-info/top_level.txt
django_storedqueries-0.1.4.dist-info/RECORD
