Metadata-Version: 2.1
Name: django-storedqueries
Version: 0.1.4
Summary: A small package for Django to ease the creation of temporary tables, based on model definitions and querysets
Home-page: https://github.com/kezabelle/django-storedqueries
Author: Keryn Knight
Author-email: django-storedqueries@kerynknight.com
Maintainer: Keryn Knight
Maintainer-email: django-storedqueries@kerynknight.com
License: BSD License
Keywords: django orm temporary tables queries
Platform: UNKNOWN
Classifier: Development Status :: 3 - Alpha
Classifier: Intended Audience :: Developers
Classifier: License :: OSI Approved :: BSD License
Classifier: Natural Language :: English
Classifier: Programming Language :: Python :: 2
Classifier: Programming Language :: Python :: 2.7
Classifier: Programming Language :: Python :: 3
Classifier: Programming Language :: Python :: 3.5
Classifier: Framework :: Django
Classifier: Framework :: Django :: 1.4
Classifier: Framework :: Django :: 1.5
Classifier: Framework :: Django :: 1.6
Classifier: Framework :: Django :: 1.7
Classifier: Framework :: Django :: 1.8
Classifier: Framework :: Django :: 1.9
Classifier: Framework :: Django :: 1.10
Classifier: Framework :: Django :: 1.11
Requires-Dist: Django (>=1.4)
